odoo8_addon_website_multi_image-8.0.1.0.0.99.dev3-py2.7-nspkg.pth
odoo8_addon_website_multi_image-8.0.1.0.0.99.dev3.dist-info/DESCRIPTION.rst
odoo8_addon_website_multi_image-8.0.1.0.0.99.dev3.dist-info/METADATA
odoo8_addon_website_multi_image-8.0.1.0.0.99.dev3.dist-info/RECORD
odoo8_addon_website_multi_image-8.0.1.0.0.99.dev3.dist-info/WHEEL
odoo8_addon_website_multi_image-8.0.1.0.0.99.dev3.dist-info/metadata.json
odoo8_addon_website_multi_image-8.0.1.0.0.99.dev3.dist-info/namespace_packages.txt
odoo8_addon_website_multi_image-8.0.1.0.0.99.dev3.dist-info/top_level.txt
odoo_addons/website_multi_image/README.rst
odoo_addons/website_multi_image/__init__.py
odoo_addons/website_multi_image/__openerp__.py
odoo_addons/website_multi_image/i18n/website_multi_image.pot
odoo_addons/website_multi_image/static/description/icon.png
odoo_addons/website_multi_image/static/description/icon.svg
odoo_addons/website_multi_image/static/src/css/website_multi_image.css
odoo_addons/website_multi_image/static/src/css/website_multi_image.css.map
odoo_addons/website_multi_image/static/src/css/website_multi_image.sass
odoo_addons/website_multi_image/views/assets.xml
odoo_addons/website_multi_image/views/owner_templates.xml
